[
    {
        "author": "6f4eaa79-649f-406e-a72b-a8e2de5f7d71",
        "authorScore": 215429,
        "bronzeScore": 324000,
        "collectionName": "Stadium",
        "createdWithGamepadEditor": null,
        "createdWithSimpleEditor": null,
        "filename": "Lunatic Winter 2023 - 11.Map.Gbx",
        "goldScore": 229000,
        "isPlayable": true,
        "mapId": "e70688f1-c19a-46b4-955c-b4293401260c",
        "mapStyle": "",
        "mapType": "TrackMania\\TM_Race",
        "mapUid": "PmSykTqhLTjRUozCSNJm4cxD7Z3",
        "name": "Lunatic Winter 2023 - 11",
        "silverScore": 259000,
        "submitter": "6f4eaa79-649f-406e-a72b-a8e2de5f7d71",
        "timestamp": "2023-02-22T13:05:06+00:00",
        "fileUrl": "https://core.trackmania.nadeo.live/maps/e70688f1-c19a-46b4-955c-b4293401260c/file",
        "thumbnailUrl": "https://core.trackmania.nadeo.live/maps/e70688f1-c19a-46b4-955c-b4293401260c/thumbnail.jpg"
    },
    {
        "author": "6f4eaa79-649f-406e-a72b-a8e2de5f7d71",
        "authorScore": 39981,
        "bronzeScore": 60000,
        "collectionName": "Stadium",
        "createdWithGamepadEditor": null,
        "createdWithSimpleEditor": null,
        "filename": "Lunatic Winter 2023 - 03.Map.Gbx",
        "goldScore": 43000,
        "isPlayable": true,
        "mapId": "b24cd422-9ba9-463d-9ca5-354e0ca38a06",
        "mapStyle": "",
        "mapType": "TrackMania\\TM_Race",
        "mapUid": "Ro15HQEDhKaTNfezhabVI0bRFJc",
        "name": "Lunatic Winter 2023 - 03",
        "silverScore": 48000,
        "submitter": "6f4eaa79-649f-406e-a72b-a8e2de5f7d71",
        "timestamp": "2023-02-22T13:04:21+00:00",
        "fileUrl": "https://core.trackmania.nadeo.live/maps/b24cd422-9ba9-463d-9ca5-354e0ca38a06/file",
        "thumbnailUrl": "https://core.trackmania.nadeo.live/maps/b24cd422-9ba9-463d-9ca5-354e0ca38a06/thumbnail.jpg"
    },
    {
        "author": "6f4eaa79-649f-406e-a72b-a8e2de5f7d71",
        "authorScore": 239088,
        "bronzeScore": 359000,
        "collectionName": "Stadium",
        "createdWithGamepadEditor": null,
        "createdWithSimpleEditor": null,
        "filename": "Lunatic Winter 2023 - 23.Map.Gbx",
        "goldScore": 254000,
        "isPlayable": true,
        "mapId": "63a64c09-bd55-4c73-a617-3432a022e08b",
        "mapStyle": "",
        "mapType": "TrackMania\\TM_Race",
        "mapUid": "tQ4XS_FePZrgpNkkQiEXxvYez61",
        "name": "Lunatic Winter 2023 - 23",
        "silverScore": 287000,
        "submitter": "6f4eaa79-649f-406e-a72b-a8e2de5f7d71",
        "timestamp": "2023-02-22T17:05:16+00:00",
        "fileUrl": "https://core.trackmania.nadeo.live/maps/63a64c09-bd55-4c73-a617-3432a022e08b/file",
        "thumbnailUrl": "https://core.trackmania.nadeo.live/maps/63a64c09-bd55-4c73-a617-3432a022e08b/thumbnail.jpg"
    },
    {
        "author": "6f4eaa79-649f-406e-a72b-a8e2de5f7d71",
        "authorScore": 185087,
        "bronzeScore": 278000,
        "collectionName": "Stadium",
        "createdWithGamepadEditor": null,
        "createdWithSimpleEditor": null,
        "filename": "Lunatic Winter 2023 - 21.Map.Gbx",
        "goldScore": 197000,
        "isPlayable": true,
        "mapId": "5b494c86-1362-4529-be28-f4b3c5719bb2",
        "mapStyle": "",
        "mapType": "TrackMania\\TM_Race",
        "mapUid": "0eMjNwdBB0PUdXGycktuS8m68i1",
        "name": "Lunatic Winter 2023 - 21",
        "silverScore": 223000,
        "submitter": "6f4eaa79-649f-406e-a72b-a8e2de5f7d71",
        "timestamp": "2023-02-22T17:05:13+00:00",
        "fileUrl": "https://core.trackmania.nadeo.live/maps/5b494c86-1362-4529-be28-f4b3c5719bb2/file",
        "thumbnailUrl": "https://core.trackmania.nadeo.live/maps/5b494c86-1362-4529-be28-f4b3c5719bb2/thumbnail.jpg"
    },
    {
        "author": "6f4eaa79-649f-406e-a72b-a8e2de5f7d71",
        "authorScore": 221609,
        "bronzeScore": 333000,
        "collectionName": "Stadium",
        "createdWithGamepadEditor": null,
        "createdWithSimpleEditor": null,
        "filename": "Lunatic Winter 2023 - 16.Map.Gbx",
        "goldScore": 235000,
        "isPlayable": true,
        "mapId": "8b806866-92c6-4560-a66f-e8f1deb06d1f",
        "mapStyle": "",
        "mapType": "TrackMania\\TM_Race",
        "mapUid": "GPHuCn5Pjy6fyZa34gRoX0K6pp6",
        "name": "Lunatic Winter 2023 - 16",
        "silverScore": 266000,
        "submitter": "6f4eaa79-649f-406e-a72b-a8e2de5f7d71",
        "timestamp": "2023-02-22T13:05:31+00:00",
        "fileUrl": "https://core.trackmania.nadeo.live/maps/8b806866-92c6-4560-a66f-e8f1deb06d1f/file",
        "thumbnailUrl": "https://core.trackmania.nadeo.live/maps/8b806866-92c6-4560-a66f-e8f1deb06d1f/thumbnail.jpg"
    },
    {
        "author": "6f4eaa79-649f-406e-a72b-a8e2de5f7d71",
        "authorScore": 214849,
        "bronzeScore": 323000,
        "collectionName": "Stadium",
        "createdWithGamepadEditor": null,
        "createdWithSimpleEditor": null,
        "filename": "Lunatic Winter 2023 - 20.Map.Gbx",
        "goldScore": 228000,
        "isPlayable": true,
        "mapId": "a14c09a6-32d7-46c2-8d29-443f94155261",
        "mapStyle": "",
        "mapType": "TrackMania\\TM_Race",
        "mapUid": "YzwfxZZvKzAUuXJ2N5sVUdv7qe0",
        "name": "Lunatic Winter 2023 - 20",
        "silverScore": 258000,
        "submitter": "6f4eaa79-649f-406e-a72b-a8e2de5f7d71",
        "timestamp": "2023-02-22T17:05:12+00:00",
        "fileUrl": "https://core.trackmania.nadeo.live/maps/a14c09a6-32d7-46c2-8d29-443f94155261/file",
        "thumbnailUrl": "https://core.trackmania.nadeo.live/maps/a14c09a6-32d7-46c2-8d29-443f94155261/thumbnail.jpg"
    },
    {
        "author": "6f4eaa79-649f-406e-a72b-a8e2de5f7d71",
        "authorScore": 150879,
        "bronzeScore": 227000,
        "collectionName": "Stadium",
        "createdWithGamepadEditor": null,
        "createdWithSimpleEditor": null,
        "filename": "Lunatic Winter 2023 - 04.Map.Gbx",
        "goldScore": 160000,
        "isPlayable": true,
        "mapId": "4f5d8947-5521-46a8-b768-d58d3cf25555",
        "mapStyle": "",
        "mapType": "TrackMania\\TM_Race",
        "mapUid": "kLbW6ItV7Z97cRtH81fc6svTZSl",
        "name": "Lunatic Winter 2023 - 04",
        "silverScore": 182000,
        "submitter": "6f4eaa79-649f-406e-a72b-a8e2de5f7d71",
        "timestamp": "2023-02-22T13:04:23+00:00",
        "fileUrl": "https://core.trackmania.nadeo.live/maps/4f5d8947-5521-46a8-b768-d58d3cf25555/file",
        "thumbnailUrl": "https://core.trackmania.nadeo.live/maps/4f5d8947-5521-46a8-b768-d58d3cf25555/thumbnail.jpg"
    },
    {
        "author": "6f4eaa79-649f-406e-a72b-a8e2de5f7d71",
        "authorScore": 36873,
        "bronzeScore": 56000,
        "collectionName": "Stadium",
        "createdWithGamepadEditor": null,
        "createdWithSimpleEditor": null,
        "filename": "Lunatic Winter 2023 - 01.Map.Gbx",
        "goldScore": 40000,
        "isPlayable": true,
        "mapId": "b23724f7-10f0-4d47-af69-d4a98db4b454",
        "mapStyle": "",
        "mapType": "TrackMania\\TM_Race",
        "mapUid": "vXMBOvPlMPyCOD2eAoJRA7IBpM3",
        "name": "Lunatic Winter 2023 - 01",
        "silverScore": 45000,
        "submitter": "6f4eaa79-649f-406e-a72b-a8e2de5f7d71",
        "timestamp": "2023-02-22T13:04:20+00:00",
        "fileUrl": "https://core.trackmania.nadeo.live/maps/b23724f7-10f0-4d47-af69-d4a98db4b454/file",
        "thumbnailUrl": "https://core.trackmania.nadeo.live/maps/b23724f7-10f0-4d47-af69-d4a98db4b454/thumbnail.jpg"
    },
    {
        "author": "6f4eaa79-649f-406e-a72b-a8e2de5f7d71",
        "authorScore": 252145,
        "bronzeScore": 379000,
        "collectionName": "Stadium",
        "createdWithGamepadEditor": null,
        "createdWithSimpleEditor": null,
        "filename": "Lunatic Winter 2023 - 19.Map.Gbx",
        "goldScore": 268000,
        "isPlayable": true,
        "mapId": "57a12728-2bdb-4a13-99d4-09389f4954a4",
        "mapStyle": "",
        "mapType": "TrackMania\\TM_Race",
        "mapUid": "xfED5qlxuLfLifFBigm982QU6x0",
        "name": "Lunatic Winter 2023 - 19",
        "silverScore": 303000,
        "submitter": "6f4eaa79-649f-406e-a72b-a8e2de5f7d71",
        "timestamp": "2023-02-22T17:05:10+00:00",
        "fileUrl": "https://core.trackmania.nadeo.live/maps/57a12728-2bdb-4a13-99d4-09389f4954a4/file",
        "thumbnailUrl": "https://core.trackmania.nadeo.live/maps/57a12728-2bdb-4a13-99d4-09389f4954a4/thumbnail.jpg"
    },
    {
        "author": "6f4eaa79-649f-406e-a72b-a8e2de5f7d71",
        "authorScore": 60214,
        "bronzeScore": 91000,
        "collectionName": "Stadium",
        "createdWithGamepadEditor": null,
        "createdWithSimpleEditor": null,
        "filename": "Lunatic Winter 2023 - 10.Map.Gbx",
        "goldScore": 64000,
        "isPlayable": true,
        "mapId": "e6ac48d9-36d5-4822-886d-ee9fa1f1f686",
        "mapStyle": "",
        "mapType": "TrackMania\\TM_Race",
        "mapUid": "8T36PFEhawc5LRiEIsGkOT7D5l5",
        "name": "Lunatic Winter 2023 - 10",
        "silverScore": 73000,
        "submitter": "6f4eaa79-649f-406e-a72b-a8e2de5f7d71",
        "timestamp": "2023-02-22T13:04:51+00:00",
        "fileUrl": "https://core.trackmania.nadeo.live/maps/e6ac48d9-36d5-4822-886d-ee9fa1f1f686/file",
        "thumbnailUrl": "https://core.trackmania.nadeo.live/maps/e6ac48d9-36d5-4822-886d-ee9fa1f1f686/thumbnail.jpg"
    },
    {
        "author": "6f4eaa79-649f-406e-a72b-a8e2de5f7d71",
        "authorScore": 196918,
        "bronzeScore": 296000,
        "collectionName": "Stadium",
        "createdWithGamepadEditor": null,
        "createdWithSimpleEditor": null,
        "filename": "Lunatic Winter 2023 - 08.Map.Gbx",
        "goldScore": 209000,
        "isPlayable": true,
        "mapId": "0e624a3d-4bcd-45e3-8890-798542f32220",
        "mapStyle": "",
        "mapType": "TrackMania\\TM_Race",
        "mapUid": "5RzJnape565qXAEKn6WJsc0Y7gf",
        "name": "Lunatic Winter 2023 - 08",
        "silverScore": 237000,
        "submitter": "6f4eaa79-649f-406e-a72b-a8e2de5f7d71",
        "timestamp": "2023-02-22T13:04:48+00:00",
        "fileUrl": "https://core.trackmania.nadeo.live/maps/0e624a3d-4bcd-45e3-8890-798542f32220/file",
        "thumbnailUrl": "https://core.trackmania.nadeo.live/maps/0e624a3d-4bcd-45e3-8890-798542f32220/thumbnail.jpg"
    },
    {
        "author": "6b082671-4028-4ae1-ad8e-022810594300",
        "authorScore": 37533,
        "bronzeScore": 57000,
        "collectionName": "Stadium",
        "createdWithGamepadEditor": null,
        "createdWithSimpleEditor": null,
        "filename": "Harder Fall 2021 - 08.Map.Gbx",
        "goldScore": 40000,
        "isPlayable": true,
        "mapId": "e55f6ce1-7bbd-4a1c-b7a5-a55c3cc0d346",
        "mapStyle": "",
        "mapType": "TrackMania\\TM_Race",
        "mapUid": "hgtLm1NLv5w1IAjulVdTm6HZgP4",
        "name": "Harder Fall 2021 - 08",
        "silverScore": 46000,
        "submitter": "6b082671-4028-4ae1-ad8e-022810594300",
        "timestamp": "2021-11-29T19:51:07+00:00",
        "fileUrl": "https://core.trackmania.nadeo.live/maps/e55f6ce1-7bbd-4a1c-b7a5-a55c3cc0d346/file",
        "thumbnailUrl": "https://core.trackmania.nadeo.live/maps/e55f6ce1-7bbd-4a1c-b7a5-a55c3cc0d346/thumbnail.jpg"
    },
    {
        "author": "6f4eaa79-649f-406e-a72b-a8e2de5f7d71",
        "authorScore": 133042,
        "bronzeScore": 200000,
        "collectionName": "Stadium",
        "createdWithGamepadEditor": null,
        "createdWithSimpleEditor": null,
        "filename": "Lunatic Winter 2023 - 15.Map.Gbx",
        "goldScore": 142000,
        "isPlayable": true,
        "mapId": "2f9e4d8e-7dc4-4f7a-bb8b-1e24e5fb50e1",
        "mapStyle": "",
        "mapType": "TrackMania\\TM_Race",
        "mapUid": "odGnvP4w5NTPX63SqZzK7YH8y1j",
        "name": "Lunatic Winter 2023 - 15",
        "silverScore": 160000,
        "submitter": "6f4eaa79-649f-406e-a72b-a8e2de5f7d71",
        "timestamp": "2023-02-22T13:05:11+00:00",
        "fileUrl": "https://core.trackmania.nadeo.live/maps/2f9e4d8e-7dc4-4f7a-bb8b-1e24e5fb50e1/file",
        "thumbnailUrl": "https://core.trackmania.nadeo.live/maps/2f9e4d8e-7dc4-4f7a-bb8b-1e24e5fb50e1/thumbnail.jpg"
    },
    {
        "author": "6f4eaa79-649f-406e-a72b-a8e2de5f7d71",
        "authorScore": 60495,
        "bronzeScore": 91000,
        "collectionName": "Stadium",
        "createdWithGamepadEditor": null,
        "createdWithSimpleEditor": null,
        "filename": "Lunatic Winter 2023 - 07.Map.Gbx",
        "goldScore": 65000,
        "isPlayable": true,
        "mapId": "e9b90e38-f330-412e-8535-592bd4a0e1f8",
        "mapStyle": "",
        "mapType": "TrackMania\\TM_Race",
        "mapUid": "ZBSLphuFiqIfAH0SMN3upXg1o46",
        "name": "Lunatic Winter 2023 - 07",
        "silverScore": 73000,
        "submitter": "6f4eaa79-649f-406e-a72b-a8e2de5f7d71",
        "timestamp": "2023-02-22T13:04:47+00:00",
        "fileUrl": "https://core.trackmania.nadeo.live/maps/e9b90e38-f330-412e-8535-592bd4a0e1f8/file",
        "thumbnailUrl": "https://core.trackmania.nadeo.live/maps/e9b90e38-f330-412e-8535-592bd4a0e1f8/thumbnail.jpg"
    },
    {
        "author": "6b082671-4028-4ae1-ad8e-022810594300",
        "authorScore": 156321,
        "bronzeScore": 235000,
        "collectionName": "Stadium",
        "createdWithGamepadEditor": null,
        "createdWithSimpleEditor": null,
        "filename": "Harder Fall 2021 - 11.Map.Gbx",
        "goldScore": 166000,
        "isPlayable": true,
        "mapId": "729e84e6-7f72-4c93-a664-fa4526b3006e",
        "mapStyle": "",
        "mapType": "TrackMania\\TM_Race",
        "mapUid": "CxuUA3h8IEdTqqRJ9SrBzNaFw_d",
        "name": "Harder Fall 2021 - 11",
        "silverScore": 188000,
        "submitter": "6b082671-4028-4ae1-ad8e-022810594300",
        "timestamp": "2021-11-29T19:51:06+00:00",
        "fileUrl": "https://core.trackmania.nadeo.live/maps/729e84e6-7f72-4c93-a664-fa4526b3006e/file",
        "thumbnailUrl": "https://core.trackmania.nadeo.live/maps/729e84e6-7f72-4c93-a664-fa4526b3006e/thumbnail.jpg"
    },
    {
        "author": "6b082671-4028-4ae1-ad8e-022810594300",
        "authorScore": 60438,
        "bronzeScore": 91000,
        "collectionName": "Stadium",
        "createdWithGamepadEditor": null,
        "createdWithSimpleEditor": null,
        "filename": "Harder Fall 2021 - 10.Map.Gbx",
        "goldScore": 65000,
        "isPlayable": true,
        "mapId": "8b08f9a1-bd49-4807-9bfe-4c4ce98cf8e0",
        "mapStyle": "",
        "mapType": "TrackMania\\TM_Race",
        "mapUid": "DLPhnJoeA8LigBhy7QZDbFiDms9",
        "name": "Harder Fall 2021 - 10",
        "silverScore": 73000,
        "submitter": "6b082671-4028-4ae1-ad8e-022810594300",
        "timestamp": "2021-11-29T19:51:06+00:00",
        "fileUrl": "https://core.trackmania.nadeo.live/maps/8b08f9a1-bd49-4807-9bfe-4c4ce98cf8e0/file",
        "thumbnailUrl": "https://core.trackmania.nadeo.live/maps/8b08f9a1-bd49-4807-9bfe-4c4ce98cf8e0/thumbnail.jpg"
    },
    {
        "author": "6b082671-4028-4ae1-ad8e-022810594300",
        "authorScore": 36020,
        "bronzeScore": 55000,
        "collectionName": "Stadium",
        "createdWithGamepadEditor": null,
        "createdWithSimpleEditor": null,
        "filename": "Harder Fall 2021 - 05.Map.Gbx",
        "goldScore": 39000,
        "isPlayable": true,
        "mapId": "01a8cb2e-ac1f-4289-8577-b8e1841195c0",
        "mapStyle": "",
        "mapType": "TrackMania\\TM_Race",
        "mapUid": "3c5omkdYppkMuCkLSoP7O7OxrTb",
        "name": "Harder Fall 2021 - 05",
        "silverScore": 44000,
        "submitter": "6b082671-4028-4ae1-ad8e-022810594300",
        "timestamp": "2021-11-29T19:51:06+00:00",
        "fileUrl": "https://core.trackmania.nadeo.live/maps/01a8cb2e-ac1f-4289-8577-b8e1841195c0/file",
        "thumbnailUrl": "https://core.trackmania.nadeo.live/maps/01a8cb2e-ac1f-4289-8577-b8e1841195c0/thumbnail.jpg"
    },
    {
        "author": "6f4eaa79-649f-406e-a72b-a8e2de5f7d71",
        "authorScore": 177677,
        "bronzeScore": 267000,
        "collectionName": "Stadium",
        "createdWithGamepadEditor": null,
        "createdWithSimpleEditor": null,
        "filename": "Lunatic Winter 2023 - 17.Map.Gbx",
        "goldScore": 189000,
        "isPlayable": true,
        "mapId": "1fb4aafe-f6b8-46f2-aeb2-8cbf4e30623c",
        "mapStyle": "",
        "mapType": "TrackMania\\TM_Race",
        "mapUid": "7wEs89agiKSg6BuAu7Bf3CwcRXd",
        "name": "Lunatic Winter 2023 - 17",
        "silverScore": 214000,
        "submitter": "6f4eaa79-649f-406e-a72b-a8e2de5f7d71",
        "timestamp": "2023-02-22T13:05:32+00:00",
        "fileUrl": "https://core.trackmania.nadeo.live/maps/1fb4aafe-f6b8-46f2-aeb2-8cbf4e30623c/file",
        "thumbnailUrl": "https://core.trackmania.nadeo.live/maps/1fb4aafe-f6b8-46f2-aeb2-8cbf4e30623c/thumbnail.jpg"
    },
    {
        "author": "6f4eaa79-649f-406e-a72b-a8e2de5f7d71",
        "authorScore": 61218,
        "bronzeScore": 92000,
        "collectionName": "Stadium",
        "createdWithGamepadEditor": null,
        "createdWithSimpleEditor": null,
        "filename": "Lunatic Winter 2023 - 09.Map.Gbx",
        "goldScore": 65000,
        "isPlayable": true,
        "mapId": "15e5c22c-908e-4a12-88ab-484e6c2843b1",
        "mapStyle": "",
        "mapType": "TrackMania\\TM_Race",
        "mapUid": "XDvUXSkNN7lou6byCuQtPaQOlxg",
        "name": "Lunatic Winter 2023 - 09",
        "silverScore": 74000,
        "submitter": "6f4eaa79-649f-406e-a72b-a8e2de5f7d71",
        "timestamp": "2023-02-22T13:04:49+00:00",
        "fileUrl": "https://core.trackmania.nadeo.live/maps/15e5c22c-908e-4a12-88ab-484e6c2843b1/file",
        "thumbnailUrl": "https://core.trackmania.nadeo.live/maps/15e5c22c-908e-4a12-88ab-484e6c2843b1/thumbnail.jpg"
    },
    {
        "author": "6b082671-4028-4ae1-ad8e-022810594300",
        "authorScore": 469066,
        "bronzeScore": 704000,
        "collectionName": "Stadium",
        "createdWithGamepadEditor": null,
        "createdWithSimpleEditor": null,
        "filename": "Harder Fall 2021 - 04.Map.Gbx",
        "goldScore": 498000,
        "isPlayable": true,
        "mapId": "f8ec76ee-140f-4d0c-a608-05a9501e9c2d",
        "mapStyle": "",
        "mapType": "TrackMania\\TM_Race",
        "mapUid": "QRyxWhumixrV7kAgrCZCrAjrTXk",
        "name": "Harder Fall 2021 - 04",
        "silverScore": 563000,
        "submitter": "6b082671-4028-4ae1-ad8e-022810594300",
        "timestamp": "2021-11-29T19:51:06+00:00",
        "fileUrl": "https://core.trackmania.nadeo.live/maps/f8ec76ee-140f-4d0c-a608-05a9501e9c2d/file",
        "thumbnailUrl": "https://core.trackmania.nadeo.live/maps/f8ec76ee-140f-4d0c-a608-05a9501e9c2d/thumbnail.jpg"
    },
    {
        "author": "6b082671-4028-4ae1-ad8e-022810594300",
        "authorScore": 46791,
        "bronzeScore": 71000,
        "collectionName": "Stadium",
        "createdWithGamepadEditor": null,
        "createdWithSimpleEditor": null,
        "filename": "Harder Fall 2021 - 03.Map.Gbx",
        "goldScore": 50000,
        "isPlayable": true,
        "mapId": "61a095c2-f535-4c0f-b919-9278c4565bdb",
        "mapStyle": "",
        "mapType": "TrackMania\\TM_Race",
        "mapUid": "Wg2UUFgDGGn3u3HswEbegUlaqri",
        "name": "Harder Fall 2021 - 03",
        "silverScore": 57000,
        "submitter": "6b082671-4028-4ae1-ad8e-022810594300",
        "timestamp": "2021-11-29T19:51:06+00:00",
        "fileUrl": "https://core.trackmania.nadeo.live/maps/61a095c2-f535-4c0f-b919-9278c4565bdb/file",
        "thumbnailUrl": "https://core.trackmania.nadeo.live/maps/61a095c2-f535-4c0f-b919-9278c4565bdb/thumbnail.jpg"
    },
    {
        "author": "6b082671-4028-4ae1-ad8e-022810594300",
        "authorScore": 22120,
        "bronzeScore": 34000,
        "collectionName": "Stadium",
        "createdWithGamepadEditor": null,
        "createdWithSimpleEditor": null,
        "filename": "Harder Fall 2021 - 02.Map.Gbx",
        "goldScore": 24000,
        "isPlayable": true,
        "mapId": "83e19c0d-9654-46f2-bad1-1f24d0b26414",
        "mapStyle": "",
        "mapType": "TrackMania\\TM_Race",
        "mapUid": "koXbGlYgXNbZxuE23tkRZ3YM3nk",
        "name": "Harder Fall 2021 - 02",
        "silverScore": 27000,
        "submitter": "6b082671-4028-4ae1-ad8e-022810594300",
        "timestamp": "2021-11-29T19:51:06+00:00",
        "fileUrl": "https://core.trackmania.nadeo.live/maps/83e19c0d-9654-46f2-bad1-1f24d0b26414/file",
        "thumbnailUrl": "https://core.trackmania.nadeo.live/maps/83e19c0d-9654-46f2-bad1-1f24d0b26414/thumbnail.jpg"
    },
    {
        "author": "6f4eaa79-649f-406e-a72b-a8e2de5f7d71",
        "authorScore": 63460,
        "bronzeScore": 96000,
        "collectionName": "Stadium",
        "createdWithGamepadEditor": null,
        "createdWithSimpleEditor": null,
        "filename": "Lunatic Winter 2023 - 06.Map.Gbx",
        "goldScore": 68000,
        "isPlayable": true,
        "mapId": "6046c1ee-ffdc-4361-b29b-48d526b9ae58",
        "mapStyle": "",
        "mapType": "TrackMania\\TM_Race",
        "mapUid": "X_IWc55Gc7oQfbB6pPFjbhto6C",
        "name": "Lunatic Winter 2023 - 06",
        "silverScore": 77000,
        "submitter": "6f4eaa79-649f-406e-a72b-a8e2de5f7d71",
        "timestamp": "2023-02-22T13:04:46+00:00",
        "fileUrl": "https://core.trackmania.nadeo.live/maps/6046c1ee-ffdc-4361-b29b-48d526b9ae58/file",
        "thumbnailUrl": "https://core.trackmania.nadeo.live/maps/6046c1ee-ffdc-4361-b29b-48d526b9ae58/thumbnail.jpg"
    },
    {
        "author": "6f4eaa79-649f-406e-a72b-a8e2de5f7d71",
        "authorScore": 78277,
        "bronzeScore": 118000,
        "collectionName": "Stadium",
        "createdWithGamepadEditor": null,
        "createdWithSimpleEditor": null,
        "filename": "Lunatic Winter 2023 - 12.Map.Gbx",
        "goldScore": 83000,
        "isPlayable": true,
        "mapId": "f6dec660-84d2-455f-8a1c-6e054663217c",
        "mapStyle": "",
        "mapType": "TrackMania\\TM_Race",
        "mapUid": "JHSrav02GHr1MChEip7FWbwned2",
        "name": "Lunatic Winter 2023 - 12",
        "silverScore": 94000,
        "submitter": "6f4eaa79-649f-406e-a72b-a8e2de5f7d71",
        "timestamp": "2023-02-22T13:05:08+00:00",
        "fileUrl": "https://core.trackmania.nadeo.live/maps/f6dec660-84d2-455f-8a1c-6e054663217c/file",
        "thumbnailUrl": "https://core.trackmania.nadeo.live/maps/f6dec660-84d2-455f-8a1c-6e054663217c/thumbnail.jpg"
    },
    {
        "author": "6b082671-4028-4ae1-ad8e-022810594300",
        "authorScore": 62581,
        "bronzeScore": 94000,
        "collectionName": "Stadium",
        "createdWithGamepadEditor": null,
        "createdWithSimpleEditor": null,
        "filename": "Harder Fall 2021 - 07 .Map.Gbx",
        "goldScore": 67000,
        "isPlayable": true,
        "mapId": "625c9343-a954-4c4b-86fd-1a1499494606",
        "mapStyle": "",
        "mapType": "TrackMania\\TM_Race",
        "mapUid": "q9ylvtyJRrdt6cboaCETeZAB8l8",
        "name": "Harder Fall 2021 - 07 ",
        "silverScore": 76000,
        "submitter": "6b082671-4028-4ae1-ad8e-022810594300",
        "timestamp": "2021-11-29T19:51:07+00:00",
        "fileUrl": "https://core.trackmania.nadeo.live/maps/625c9343-a954-4c4b-86fd-1a1499494606/file",
        "thumbnailUrl": "https://core.trackmania.nadeo.live/maps/625c9343-a954-4c4b-86fd-1a1499494606/thumbnail.jpg"
    },
    {
        "author": "6f4eaa79-649f-406e-a72b-a8e2de5f7d71",
        "authorScore": 279587,
        "bronzeScore": 420000,
        "collectionName": "Stadium",
        "createdWithGamepadEditor": null,
        "createdWithSimpleEditor": null,
        "filename": "Lunatic Winter 2023 - 22.Map.Gbx",
        "goldScore": 297000,
        "isPlayable": true,
        "mapId": "0d22275e-2110-420e-867c-6a20f06bb539",
        "mapStyle": "",
        "mapType": "TrackMania\\TM_Race",
        "mapUid": "WOFaaBe9qbzPkNM2dYBcSgW5iCj",
        "name": "Lunatic Winter 2023 - 22",
        "silverScore": 336000,
        "submitter": "6f4eaa79-649f-406e-a72b-a8e2de5f7d71",
        "timestamp": "2023-02-22T17:05:14+00:00",
        "fileUrl": "https://core.trackmania.nadeo.live/maps/0d22275e-2110-420e-867c-6a20f06bb539/file",
        "thumbnailUrl": "https://core.trackmania.nadeo.live/maps/0d22275e-2110-420e-867c-6a20f06bb539/thumbnail.jpg"
    },
    {
        "author": "6f4eaa79-649f-406e-a72b-a8e2de5f7d71",
        "authorScore": 389408,
        "bronzeScore": 585000,
        "collectionName": "Stadium",
        "createdWithGamepadEditor": null,
        "createdWithSimpleEditor": null,
        "filename": "Lunatic Winter 2023 - 24.Map.Gbx",
        "goldScore": 413000,
        "isPlayable": true,
        "mapId": "94ebbd68-6a5e-4209-b7ec-ca0e4e01281f",
        "mapStyle": "",
        "mapType": "TrackMania\\TM_Race",
        "mapUid": "4ZR2jD6yNjvfR3KxaWYCm57CYIj",
        "name": "Lunatic Winter 2023 - 24",
        "silverScore": 468000,
        "submitter": "6f4eaa79-649f-406e-a72b-a8e2de5f7d71",
        "timestamp": "2023-02-22T17:05:17+00:00",
        "fileUrl": "https://core.trackmania.nadeo.live/maps/94ebbd68-6a5e-4209-b7ec-ca0e4e01281f/file",
        "thumbnailUrl": "https://core.trackmania.nadeo.live/maps/94ebbd68-6a5e-4209-b7ec-ca0e4e01281f/thumbnail.jpg"
    },
    {
        "author": "6b082671-4028-4ae1-ad8e-022810594300",
        "authorScore": 126559,
        "bronzeScore": 190000,
        "collectionName": "Stadium",
        "createdWithGamepadEditor": null,
        "createdWithSimpleEditor": null,
        "filename": "Harder Fall 2021 - 14.Map.Gbx",
        "goldScore": 135000,
        "isPlayable": true,
        "mapId": "d05fdbb4-0690-422a-b0f5-0f4d0ee54cb7",
        "mapStyle": "",
        "mapType": "TrackMania\\TM_Race",
        "mapUid": "db2atHblg2iszwHqgmxTLpoKcIh",
        "name": "Harder Fall 2021 - 14",
        "silverScore": 152000,
        "submitter": "6b082671-4028-4ae1-ad8e-022810594300",
        "timestamp": "2021-11-29T19:51:06+00:00",
        "fileUrl": "https://core.trackmania.nadeo.live/maps/d05fdbb4-0690-422a-b0f5-0f4d0ee54cb7/file",
        "thumbnailUrl": "https://core.trackmania.nadeo.live/maps/d05fdbb4-0690-422a-b0f5-0f4d0ee54cb7/thumbnail.jpg"
    },
    {
        "author": "6b082671-4028-4ae1-ad8e-022810594300",
        "authorScore": 436684,
        "bronzeScore": 656000,
        "collectionName": "Stadium",
        "createdWithGamepadEditor": null,
        "createdWithSimpleEditor": null,
        "filename": "Harder Fall 2021 - 15.Map.Gbx",
        "goldScore": 463000,
        "isPlayable": true,
        "mapId": "97469b88-3608-41f9-8f4a-b462279a1b8e",
        "mapStyle": "",
        "mapType": "TrackMania\\TM_Race",
        "mapUid": "NyatgpSRHZUXIZ7EwjERXcLWS5h",
        "name": "Harder Fall 2021 - 15",
        "silverScore": 525000,
        "submitter": "6b082671-4028-4ae1-ad8e-022810594300",
        "timestamp": "2021-11-29T19:51:06+00:00",
        "fileUrl": "https://core.trackmania.nadeo.live/maps/97469b88-3608-41f9-8f4a-b462279a1b8e/file",
        "thumbnailUrl": "https://core.trackmania.nadeo.live/maps/97469b88-3608-41f9-8f4a-b462279a1b8e/thumbnail.jpg"
    },
    {
        "author": "6f4eaa79-649f-406e-a72b-a8e2de5f7d71",
        "authorScore": 236767,
        "bronzeScore": 356000,
        "collectionName": "Stadium",
        "createdWithGamepadEditor": null,
        "createdWithSimpleEditor": null,
        "filename": "Lunatic Winter 2023 - 25.Map.Gbx",
        "goldScore": 251000,
        "isPlayable": true,
        "mapId": "7ca7322d-8c52-42de-851a-acec3b62ddc7",
        "mapStyle": "",
        "mapType": "TrackMania\\TM_Race",
        "mapUid": "Lq_lIX02T7v9EWOIeBYt3EgOTM1",
        "name": "Lunatic Winter 2023 - 25",
        "silverScore": 285000,
        "submitter": "6f4eaa79-649f-406e-a72b-a8e2de5f7d71",
        "timestamp": "2023-02-22T17:05:19+00:00",
        "fileUrl": "https://core.trackmania.nadeo.live/maps/7ca7322d-8c52-42de-851a-acec3b62ddc7/file",
        "thumbnailUrl": "https://core.trackmania.nadeo.live/maps/7ca7322d-8c52-42de-851a-acec3b62ddc7/thumbnail.jpg"
    },
    {
        "author": "6f4eaa79-649f-406e-a72b-a8e2de5f7d71",
        "authorScore": 121005,
        "bronzeScore": 182000,
        "collectionName": "Stadium",
        "createdWithGamepadEditor": null,
        "createdWithSimpleEditor": null,
        "filename": "Lunatic Winter 2023 - 13.Map.Gbx",
        "goldScore": 129000,
        "isPlayable": true,
        "mapId": "22b07ac0-6cb0-408b-b55e-f0ad11ef773f",
        "mapStyle": "",
        "mapType": "TrackMania\\TM_Race",
        "mapUid": "6ZBXVV92ymw_dyJ3vO9utmbJeTg",
        "name": "Lunatic Winter 2023 - 13",
        "silverScore": 146000,
        "submitter": "6f4eaa79-649f-406e-a72b-a8e2de5f7d71",
        "timestamp": "2023-02-22T13:05:09+00:00",
        "fileUrl": "https://core.trackmania.nadeo.live/maps/22b07ac0-6cb0-408b-b55e-f0ad11ef773f/file",
        "thumbnailUrl": "https://core.trackmania.nadeo.live/maps/22b07ac0-6cb0-408b-b55e-f0ad11ef773f/thumbnail.jpg"
    },
    {
        "author": "6f4eaa79-649f-406e-a72b-a8e2de5f7d71",
        "authorScore": 54365,
        "bronzeScore": 82000,
        "collectionName": "Stadium",
        "createdWithGamepadEditor": null,
        "createdWithSimpleEditor": null,
        "filename": "Lunatic Winter 2023 - 05.Map.Gbx",
        "goldScore": 58000,
        "isPlayable": true,
        "mapId": "b093f774-200e-4913-9c8c-6ef285e4524f",
        "mapStyle": "",
        "mapType": "TrackMania\\TM_Race",
        "mapUid": "dY2UdaCRqgkxpBtEmRXTwkiTdPf",
        "name": "Lunatic Winter 2023 - 05",
        "silverScore": 66000,
        "submitter": "6f4eaa79-649f-406e-a72b-a8e2de5f7d71",
        "timestamp": "2023-02-22T13:04:24+00:00",
        "fileUrl": "https://core.trackmania.nadeo.live/maps/b093f774-200e-4913-9c8c-6ef285e4524f/file",
        "thumbnailUrl": "https://core.trackmania.nadeo.live/maps/b093f774-200e-4913-9c8c-6ef285e4524f/thumbnail.jpg"
    },
    {
        "author": "6f4eaa79-649f-406e-a72b-a8e2de5f7d71",
        "authorScore": 56456,
        "bronzeScore": 85000,
        "collectionName": "Stadium",
        "createdWithGamepadEditor": null,
        "createdWithSimpleEditor": null,
        "filename": "Lunatic Winter 2023 - 02.Map.Gbx",
        "goldScore": 60000,
        "isPlayable": true,
        "mapId": "c2a6cde7-65e3-4f63-bd92-9bf0a69e0322",
        "mapStyle": "",
        "mapType": "TrackMania\\TM_Race",
        "mapUid": "raDi4vABItNlGzfpyHaKOss3CCh",
        "name": "Lunatic Winter 2023 - 02",
        "silverScore": 68000,
        "submitter": "6f4eaa79-649f-406e-a72b-a8e2de5f7d71",
        "timestamp": "2023-02-22T13:04:21+00:00",
        "fileUrl": "https://core.trackmania.nadeo.live/maps/c2a6cde7-65e3-4f63-bd92-9bf0a69e0322/file",
        "thumbnailUrl": "https://core.trackmania.nadeo.live/maps/c2a6cde7-65e3-4f63-bd92-9bf0a69e0322/thumbnail.jpg"
    },
    {
        "author": "6b082671-4028-4ae1-ad8e-022810594300",
        "authorScore": 103017,
        "bronzeScore": 155000,
        "collectionName": "Stadium",
        "createdWithGamepadEditor": null,
        "createdWithSimpleEditor": null,
        "filename": "Harder Fall 2021 - 09.Map.Gbx",
        "goldScore": 110000,
        "isPlayable": true,
        "mapId": "155ae0b1-53ed-4ca1-948f-2eaff273274e",
        "mapStyle": "",
        "mapType": "TrackMania\\TM_Race",
        "mapUid": "devNNrSAuJ1KpjfqS4WmVGRGB4h",
        "name": "Harder Fall 2021 - 09",
        "silverScore": 124000,
        "submitter": "6b082671-4028-4ae1-ad8e-022810594300",
        "timestamp": "2021-11-29T19:51:06+00:00",
        "fileUrl": "https://core.trackmania.nadeo.live/maps/155ae0b1-53ed-4ca1-948f-2eaff273274e/file",
        "thumbnailUrl": "https://core.trackmania.nadeo.live/maps/155ae0b1-53ed-4ca1-948f-2eaff273274e/thumbnail.jpg"
    },
    {
        "author": "6f4eaa79-649f-406e-a72b-a8e2de5f7d71",
        "authorScore": 125932,
        "bronzeScore": 189000,
        "collectionName": "Stadium",
        "createdWithGamepadEditor": null,
        "createdWithSimpleEditor": null,
        "filename": "Lunatic Winter 2023 - 18.Map.Gbx",
        "goldScore": 134000,
        "isPlayable": true,
        "mapId": "744f1008-520f-41e7-bf93-f57180b4ad67",
        "mapStyle": "",
        "mapType": "TrackMania\\TM_Race",
        "mapUid": "v6NMZUlMO0XBB4ON2VpcUEXApEc",
        "name": "Lunatic Winter 2023 - 18",
        "silverScore": 152000,
        "submitter": "6f4eaa79-649f-406e-a72b-a8e2de5f7d71",
        "timestamp": "2023-02-22T17:05:09+00:00",
        "fileUrl": "https://core.trackmania.nadeo.live/maps/744f1008-520f-41e7-bf93-f57180b4ad67/file",
        "thumbnailUrl": "https://core.trackmania.nadeo.live/maps/744f1008-520f-41e7-bf93-f57180b4ad67/thumbnail.jpg"
    },
    {
        "author": "6f4eaa79-649f-406e-a72b-a8e2de5f7d71",
        "authorScore": 120594,
        "bronzeScore": 181000,
        "collectionName": "Stadium",
        "createdWithGamepadEditor": null,
        "createdWithSimpleEditor": null,
        "filename": "Lunatic Winter 2023 - 14.Map.Gbx",
        "goldScore": 128000,
        "isPlayable": true,
        "mapId": "0637f29f-36f7-4f54-9128-2061cfb741ed",
        "mapStyle": "",
        "mapType": "TrackMania\\TM_Race",
        "mapUid": "1XhwhNLBopICquFa8Ug1XvpaSxm",
        "name": "Lunatic Winter 2023 - 14",
        "silverScore": 145000,
        "submitter": "6f4eaa79-649f-406e-a72b-a8e2de5f7d71",
        "timestamp": "2023-02-22T13:05:10+00:00",
        "fileUrl": "https://core.trackmania.nadeo.live/maps/0637f29f-36f7-4f54-9128-2061cfb741ed/file",
        "thumbnailUrl": "https://core.trackmania.nadeo.live/maps/0637f29f-36f7-4f54-9128-2061cfb741ed/thumbnail.jpg"
    },
    {
        "author": "6b082671-4028-4ae1-ad8e-022810594300",
        "authorScore": 111395,
        "bronzeScore": 168000,
        "collectionName": "Stadium",
        "createdWithGamepadEditor": null,
        "createdWithSimpleEditor": null,
        "filename": "Harder Fall 2021 - 12.Map.Gbx",
        "goldScore": 119000,
        "isPlayable": true,
        "mapId": "98ce60ef-1764-44fa-8896-05d0cfea9592",
        "mapStyle": "",
        "mapType": "TrackMania\\TM_Race",
        "mapUid": "cjd7kgAaeceRvW1q5zUxwEw4lb",
        "name": "Harder Fall 2021 - 12",
        "silverScore": 134000,
        "submitter": "6b082671-4028-4ae1-ad8e-022810594300",
        "timestamp": "2021-11-29T19:51:06+00:00",
        "fileUrl": "https://core.trackmania.nadeo.live/maps/98ce60ef-1764-44fa-8896-05d0cfea9592/file",
        "thumbnailUrl": "https://core.trackmania.nadeo.live/maps/98ce60ef-1764-44fa-8896-05d0cfea9592/thumbnail.jpg"
    },
    {
        "author": "6b082671-4028-4ae1-ad8e-022810594300",
        "authorScore": 38975,
        "bronzeScore": 59000,
        "collectionName": "Stadium",
        "createdWithGamepadEditor": null,
        "createdWithSimpleEditor": null,
        "filename": "Harder Fall 2021 - 06.Map.Gbx",
        "goldScore": 42000,
        "isPlayable": true,
        "mapId": "2c6b3c6b-1455-4ce4-b4d3-215af81e27d6",
        "mapStyle": "",
        "mapType": "TrackMania\\TM_Race",
        "mapUid": "LZMPyjw2ic37H6EkTZbHnc8j1X",
        "name": "Harder Fall 2021 - 06",
        "silverScore": 47000,
        "submitter": "6b082671-4028-4ae1-ad8e-022810594300",
        "timestamp": "2021-11-29T19:51:07+00:00",
        "fileUrl": "https://core.trackmania.nadeo.live/maps/2c6b3c6b-1455-4ce4-b4d3-215af81e27d6/file",
        "thumbnailUrl": "https://core.trackmania.nadeo.live/maps/2c6b3c6b-1455-4ce4-b4d3-215af81e27d6/thumbnail.jpg"
    },
    {
        "author": "6b082671-4028-4ae1-ad8e-022810594300",
        "authorScore": 49571,
        "bronzeScore": 75000,
        "collectionName": "Stadium",
        "createdWithGamepadEditor": null,
        "createdWithSimpleEditor": null,
        "filename": "Harder Fall 2021 - 01.Map.Gbx",
        "goldScore": 53000,
        "isPlayable": true,
        "mapId": "57d22b60-8109-4ed1-ad27-dcb4bfb5275a",
        "mapStyle": "",
        "mapType": "TrackMania\\TM_Race",
        "mapUid": "oGCvMCIF7bEX_7qMcL_NoULVUmh",
        "name": "Harder Fall 2021 - 01",
        "silverScore": 60000,
        "submitter": "6b082671-4028-4ae1-ad8e-022810594300",
        "timestamp": "2021-11-29T19:51:06+00:00",
        "fileUrl": "https://core.trackmania.nadeo.live/maps/57d22b60-8109-4ed1-ad27-dcb4bfb5275a/file",
        "thumbnailUrl": "https://core.trackmania.nadeo.live/maps/57d22b60-8109-4ed1-ad27-dcb4bfb5275a/thumbnail.jpg"
    },
    {
        "author": "6b082671-4028-4ae1-ad8e-022810594300",
        "authorScore": 611923,
        "bronzeScore": 918000,
        "collectionName": "Stadium",
        "createdWithGamepadEditor": null,
        "createdWithSimpleEditor": null,
        "filename": "Harder Fall 2021 - 13.Map.Gbx",
        "goldScore": 649000,
        "isPlayable": true,
        "mapId": "effe8862-3820-47e8-b58d-586d898341be",
        "mapStyle": "",
        "mapType": "TrackMania\\TM_Race",
        "mapUid": "7ALHiCuNHJSiqDyNtmDWWBfjFzd",
        "name": "Harder Fall 2021 - 13",
        "silverScore": 735000,
        "submitter": "6b082671-4028-4ae1-ad8e-022810594300",
        "timestamp": "2021-11-29T19:51:06+00:00",
        "fileUrl": "https://core.trackmania.nadeo.live/maps/effe8862-3820-47e8-b58d-586d898341be/file",
        "thumbnailUrl": "https://core.trackmania.nadeo.live/maps/effe8862-3820-47e8-b58d-586d898341be/thumbnail.jpg"
    }
]